{
  "v": "5.6.6",
  "ip": 0,
  "op": 160,
  "fr": 60,
  "w": 800,
  "h": 800,
  "layers": [
    {
      "ind": 5368,
      "nm": "surface17735",
      "ao": 0,
      "ip": 0,
      "op": 264,
      "st": 0,
      "ty": 4,
      "ks": {
        "ty": "tr",
        "o": {
          "k": 100
        },
        "r": {
          "k": 0
        },
        "p": {
          "k": [
            0,
            0
          ]
        },
        "a": {
          "k": [
            0,
            0
          ]
        },
        "s": {
          "k": [
            133.33,
            133.33
          ]
        },
        "sk": {
          "k": 0
        },
        "sa": {
          "k": 0
        }
      },
      "shapes": [
        {
          "ty": "gr",
          "hd": false,
          "nm": "surface17735",
          "it": [
            {
              "ty": "gr",
              "hd": false,
              "it": [
                {
                  "ty": "sh",
                  "ks": {
                    "k": {
                      "i": [
                        [
                          0,
                          0
                        ],
                        [
                          0,
                          0
                        ]
                      ],
                      "o": [
                        [
                          0,
                          0
                        ],
                        [
                          0,
                          0
                        ]
                      ],
                      "v": [
                        [
                          8,
                          16
                        ],
                        [
                          2,
                          16
                        ]
                      ],
                      "c": false
                    }
                  }
                },
                {
                  "ty": "sh",
                  "ks": {
                    "k": {
                      "i": [
                        [
                          0,
                          0
                        ],
                        [
                          0,
                          0
                        ]
                      ],
                      "o": [
                        [
                          0,
                          0
                        ],
                        [
                          0,
                          0
                        ]
                      ],
                      "v": [
                        [
                          9,
                          20
                        ],
                        [
                          3,
                          20
                        ]
                      ],
                      "c": false
                    }
                  }
                },
                {
                  "ty": "sh",
                  "ks": {
                    "k": {
                      "i": [
                        [
                          0,
                          0
                        ],
                        [
                          0,
                          0
                        ]
                      ],
                      "o": [
                        [
                          0,
                          0
                        ],
                        [
                          0,
                          0
                        ]
                      ],
                      "v": [
                        [
                          7,
                          12
                        ],
                        [
                          1,
                          12
                        ]
                      ],
                      "c": false
                    }
                  }
                },
                {
                  "ty": "sh",
                  "ks": {
                    "k": {
                      "i": [
                        [
                          0,
                          0
                        ],
                        [
                          0,
                          0
                        ]
                      ],
                      "o": [
                        [
                          0,
                          0
                        ],
                        [
                          0,
                          0
                        ]
                      ],
                      "v": [
                        [
                          26,
                          16
                        ],
                        [
                          11,
                          16
                        ]
                      ],
                      "c": false
                    }
                  }
                },
                {
                  "ty": "sh",
                  "ks": {
                    "k": {
                      "i": [
                        [
                          0,
                          0
                        ],
                        [
                          0,
                          0
                        ]
                      ],
                      "o": [
                        [
                          0,
                          0
                        ],
                        [
                          0,
                          0
                        ]
                      ],
                      "v": [
                        [
                          25,
                          20
                        ],
                        [
                          12,
                          20
                        ]
                      ],
                      "c": false
                    }
                  }
                },
                {
                  "ty": "sh",
                  "ks": {
                    "k": {
                      "i": [
                        [
                          0,
                          0
                        ],
                        [
                          0,
                          0
                        ]
                      ],
                      "o": [
                        [
                          0,
                          0
                        ],
                        [
                          0,
                          0
                        ]
                      ],
                      "v": [
                        [
                          27,
                          12
                        ],
                        [
                          10,
                          12
                        ]
                      ],
                      "c": false
                    }
                  }
                },
                {
                  "ty": "sh",
                  "ks": {
                    "k": {
                      "i": [
                        [
                          0,
                          0
                        ],
                        [
                          0,
                          0
                        ],
                        [
                          -0.14,
                          1.04
                        ],
                        [
                          0,
                          0
                        ],
                        [
                          0,
                          0
                        ],
                        [
                          0,
                          0
                        ],
                        [
                          0,
                          0
                        ]
                      ],
                      "o": [
                        [
                          0,
                          0
                        ],
                        [
                          1.12,
                          0
                        ],
                        [
                          0,
                          0
                        ],
                        [
                          0,
                          0
                        ],
                        [
                          0,
                          0
                        ],
                        [
                          0,
                          0
                        ],
                        [
                          0,
                          0
                        ]
                      ],
                      "v": [
                        [
                          10,
                          24
                        ],
                        [
                          27,
                          24
                        ],
                        [
                          29,
                          22
                        ],
                        [
                          31,
                          8
                        ],
                        [
                          6,
                          8
                        ],
                        [
                          4,
                          1
                        ],
                        [
                          1,
                          1
                        ]
                      ],
                      "c": false
                    }
                  }
                },
                {
                  "ty": "sh",
                  "ks": {
                    "k": {
                      "i": [
                        [
                          0,
                          0
                        ],
                        [
                          1.1,
                          0
                        ],
                        [
                          0,
                          -1.1
                        ],
                        [
                          -1.1,
                          0
                        ],
                        [
                          0,
                          1.1
                        ]
                      ],
                      "o": [
                        [
                          0,
                          -1.1
                        ],
                        [
                          -1.1,
                          0
                        ],
                        [
                          0,
                          1.1
                        ],
                        [
                          1.1,
                          0
                        ],
                        [
                          0,
                          0
                        ]
                      ],
                      "v": [
                        [
                          13,
                          29
                        ],
                        [
                          11,
                          27
                        ],
                        [
                          9,
                          29
                        ],
                        [
                          11,
                          31
                        ],
                        [
                          13,
                          29
                        ]
                      ],
                      "c": true
                    }
                  }
                },
                {
                  "ty": "sh",
                  "ks": {
                    "k": {
                      "i": [
                        [
                          0,
                          0
                        ],
                        [
                          1.1,
                          0
                        ],
                        [
                          0,
                          -1.1
                        ],
                        [
                          -1.1,
                          0
                        ],
                        [
                          0,
                          1.1
                        ]
                      ],
                      "o": [
                        [
                          0,
                          -1.1
                        ],
                        [
                          -1.1,
                          0
                        ],
                        [
                          0,
                          1.1
                        ],
                        [
                          1.1,
                          0
                        ],
                        [
                          0,
                          0
                        ]
                      ],
                      "v": [
                        [
                          25,
                          29
                        ],
                        [
                          23,
                          27
                        ],
                        [
                          21,
                          29
                        ],
                        [
                          23,
                          31
                        ],
                        [
                          25,
                          29
                        ]
                      ],
                      "c": true
                    }
                  }
                },
                {
                  "ty": "st",
                  "lc": 2,
                  "lj": 2,
                  "ml": 4,
                  "o": {
                    "k": 100
                  },
                  "w": {
                    "k": 2
                  },
                  "c": {
                    "k": [
                      0,
                      0,
                      0,
                      1
                    ]
                  },
                  "hd": false
                },
                {
                  "ty": "tr",
                  "o": {
                    "k": 100
                  },
                  "r": {
                    "k": 0
                  },
                  "p": {
                    "k": [
                      0,
                      0
                    ]
                  },
                  "a": {
                    "k": [
                      0,
                      0
                    ]
                  },
                  "s": {
                    "k": [
                      1875,
                      1875
                    ]
                  },
                  "sk": {
                    "k": 0
                  },
                  "sa": {
                    "k": 0
                  },
                  "hd": false
                }
              ]
            },
            {
              "ty": "gr",
              "hd": false,
              "it": [
                {
                  "ty": "sh",
                  "ks": {
                    "k": {
                      "i": [
                        [
                          0,
                          0
                        ],
                        [
                          0,
                          -20.62
                        ],
                        [
                          20.62,
                          0
                        ],
                        [
                          0,
                          20.62
                        ],
                        [
                          -20.62,
                          0
                        ]
                      ],
                      "o": [
                        [
                          20.62,
                          0
                        ],
                        [
                          0,
                          20.62
                        ],
                        [
                          -20.62,
                          0
                        ],
                        [
                          0,
                          -20.62
                        ],
                        [
                          0,
                          0
                        ]
                      ],
                      "v": [
                        [
                          431.25,
                          506.25
                        ],
                        [
                          468.75,
                          543.75
                        ],
                        [
                          431.25,
                          581.25
                        ],
                        [
                          393.75,
                          543.75
                        ],
                        [
                          431.25,
                          506.25
                        ]
                      ],
                      "c": true
                    }
                  }
                },
                {
                  "ty": "sh",
                  "ks": {
                    "k": {
                      "i": [
                        [
                          0,
                          0
                        ],
                        [
                          0,
                          -20.62
                        ],
                        [
                          20.62,
                          0
                        ],
                        [
                          0,
                          20.62
                        ],
                        [
                          -20.62,
                          0
                        ]
                      ],
                      "o": [
                        [
                          20.62,
                          0
                        ],
                        [
                          0,
                          20.62
                        ],
                        [
                          -20.62,
                          0
                        ],
                        [
                          0,
                          -20.62
                        ],
                        [
                          0,
                          0
                        ]
                      ],
                      "v": [
                        [
                          206.25,
                          506.25
                        ],
                        [
                          243.75,
                          543.75
                        ],
                        [
                          206.25,
                          581.25
                        ],
                        [
                          168.75,
                          543.75
                        ],
                        [
                          206.25,
                          506.25
                        ]
                      ],
                      "c": true
                    }
                  }
                },
                {
                  "ty": "fl",
                  "o": {
                    "a": 1,
                    "k": [
                      {
                        "i": {
                          "x": [
                            0.67
                          ],
                          "y": [
                            1
                          ]
                        },
                        "o": {
                          "x": [
                            0.33
                          ],
                          "y": [
                            0
                          ]
                        },
                        "t": 59,
                        "s": [
                          0
                        ]
                      },
                      {
                        "t": 109,
                        "s": [
                          100
                        ]
                      }
                    ],
                    "ix": 5
                  },
                  "c": {
                    "k": [
                      0.4,
                      0.5,
                      0.47,
                      1
                    ]
                  }
                },
                {
                  "ty": "tr",
                  "o": {
                    "k": 100
                  },
                  "r": {
                    "k": 0
                  },
                  "p": {
                    "k": [
                      0,
                      0
                    ]
                  },
                  "a": {
                    "k": [
                      0,
                      0
                    ]
                  },
                  "s": {
                    "k": [
                      100,
                      100
                    ]
                  },
                  "sk": {
                    "k": 0
                  },
                  "sa": {
                    "k": 0
                  },
                  "hd": false
                }
              ]
            },
            {
              "ty": "gr",
              "hd": false,
              "it": [
                {
                  "ty": "sh",
                  "ks": {
                    "k": {
                      "i": [
                        [
                          0,
                          0
                        ],
                        [
                          0,
                          0
                        ],
                        [
                          0,
                          0
                        ],
                        [
                          0,
                          0
                        ],
                        [
                          21,
                          0
                        ]
                      ],
                      "o": [
                        [
                          0,
                          0
                        ],
                        [
                          0,
                          0
                        ],
                        [
                          0,
                          0
                        ],
                        [
                          -2.62,
                          19.5
                        ],
                        [
                          0,
                          0
                        ]
                      ],
                      "v": [
                        [
                          187.5,
                          450
                        ],
                        [
                          112.5,
                          150
                        ],
                        [
                          581.25,
                          150
                        ],
                        [
                          543.75,
                          412.5
                        ],
                        [
                          506.25,
                          450
                        ]
                      ],
                      "c": true
                    }
                  }
                },
                {
                  "ty": "fl",
                  "o": {
                    "a": 1,
                    "k": [
                      {
                        "i": {
                          "x": [
                            0.67
                          ],
                          "y": [
                            1
                          ]
                        },
                        "o": {
                          "x": [
                            0.33
                          ],
                          "y": [
                            0
                          ]
                        },
                        "t": 59,
                        "s": [
                          0
                        ]
                      },
                      {
                        "t": 109,
                        "s": [
                          100
                        ]
                      }
                    ],
                    "ix": 5
                  },
                  "c": {
                    "k": [
                      1,
                      0.77,
                      0.3,
                      1
                    ]
                  }
                },
                {
                  "ty": "tr",
                  "o": {
                    "k": 100
                  },
                  "r": {
                    "k": 0
                  },
                  "p": {
                    "k": [
                      0,
                      0
                    ]
                  },
                  "a": {
                    "k": [
                      0,
                      0
                    ]
                  },
                  "s": {
                    "k": [
                      100,
                      100
                    ]
                  },
                  "sk": {
                    "k": 0
                  },
                  "sa": {
                    "k": 0
                  },
                  "hd": false
                }
              ]
            },
            {
              "ty": "tr",
              "o": {
                "k": 100
              },
              "r": {
                "k": 0
              },
              "p": {
                "k": [
                  0,
                  0
                ]
              },
              "a": {
                "k": [
                  0,
                  0
                ]
              },
              "s": {
                "k": [
                  100,
                  100
                ]
              },
              "sk": {
                "k": 0
              },
              "sa": {
                "k": 0
              },
              "hd": false
            }
          ]
        },
        {
          "ty": "tm",
          "s": {
            "a": 0,
            "k": 0,
            "ix": 1
          },
          "e": {
            "a": 1,
            "k": [
              {
                "i": {
                  "x": [
                    0.27
                  ],
                  "y": [
                    1
                  ]
                },
                "o": {
                  "x": [
                    0.5
                  ],
                  "y": [
                    0
                  ]
                },
                "t": 0,
                "s": [
                  0
                ]
              },
              {
                "t": 66,
                "s": [
                  100
                ]
              }
            ],
            "ix": 2
          },
          "o": {
            "a": 0,
            "k": 0,
            "ix": 3
          },
          "m": 1,
          "ix": 2,
          "hd": false
        }
      ]
    }
  ],
  "meta": {
    "g": "LF SVG to Lottie"
  }
}